{
  "html_lang": "my",
  "per_decade_c": "°C / ဆယ်စုနှစ်",
  "per_decade_days": "ရက် / ဆယ်စုနှစ်",
  "ns": "အရေးမပါ",
  "smoothed": "ချောမွေ့စေသည် (LOESS)",
  "guide_title": "ℹ️ ဤဇယားများကို ဘယ်လိုဖတ်ရမလဲ",
  "guide_body": "<li><b>အစက်များ / တံများ</b>: တစ်နှစ်စီ၏ တန်ဖိုး။</li><li><b>အရောင်မျဉ်းကွေးထူ</b>: LOESS ချောမွေ့စေသူ၊ ဒေသဆိုင်ရာ လားရာ၊ လွတ်လပ်စွာ ကွေးနိုင်သည်၊ ထို့ကြောင့် အချိန်ကြာလာသည်နှင့်အမျှ နှုန်းပြောင်းလဲမှုကို မြင်နိုင်သည် (ဥပမာ ~၁၉၈၅ နောက်ပိုင်း ပူနွေးမှု အရှိန်မြင့်လာခြင်း)။</li><li><b>အစက်မျဉ်း</b>: ဖြောင့်တန်းသော ခိုင်မာသည့် (Theil-Sen) လားရာ၊ ၎င်း၏ စောင်းသည် ရှင်းလင်းချက်ရှိ “ဆယ်စုနှစ်တစ်ခုလျှင်” ကိန်းဂဏန်းဖြစ်သည်။</li><li><b>p&lt;0.05 / အရေးမပါ</b>: Mann-Kendall အရေးပါမှု: လားရာသည် စာရင်းအင်းအရ မှန်ကန်သလား သို့မဟုတ် ဆူညံသံသာ ဖြစ်နိုင်သလား (အရေးမပါ = စာရင်းအင်းအရ အရေးမပါ)။ အပူချိန်သည် များသောအားဖြင့် အလွန်အရေးပါသည်၊ မိုးရေချိန်မှာ မကြာခဏ မဟုတ်ပါ။</li><li><b>အရိပ်ရ တန်း</b>: ထိုလအတွက် နှစ်အားလုံး၏ ပြည့်စုံသော သမိုင်းဝင် အကွာအဝေး။</li><li><b>အပူမြေပုံ အရောင်များ</b>: အပူချိန် (အပြာ အေး → အနီ ပူ)၊ ထိုလ နှစ်များအတွင်း ပြောင်းလဲပုံ မြင်ရန် ကော်လံတစ်ခုကို အောက်မှ အပေါ်သို့ ဖတ်ပါ။</li>",
  "months": [
    "ဇန်",
    "ဖေ",
    "မတ်",
    "ဧ",
    "မေ",
    "ဇွန်",
    "ဇူ",
    "ဩ",
    "စက်",
    "အောက်",
    "နို",
    "ဒီ"
  ],
  "threshold_title": "တစ်နှစ်လျှင် ပူသောနှင့် အေးခဲသောရက်များ, {name}",
  "threshold_hot": "ပူသောရက်များ (>{t:.0f} °C)",
  "threshold_freeze": "အေးခဲသောရက်များ (<{t:.0f} °C)",
  "days_per_year": "တစ်နှစ်လျှင် ရက်များ",
  "year": "နှစ်",
  "month": "လ",
  "yearly_title": "နှစ်များအတွင်း နှစ်စဉ်ပျမ်းမျှ အပူချိန်, {name}",
  "yearly_ylabel": "နှစ်စဉ်ပျမ်းမျှ အပူချိန် (°C)",
  "annual_mean": "နှစ်စဉ်ပျမ်းမျှ",
  "trend": "လားရာ",
  "anomaly_title": "နှစ်စဉ် အပူချိန် ကွဲလွဲမှု, {name}",
  "anomaly_ylabel": "ကွဲလွဲမှု (°C)",
  "vs_baseline": "{lo}-{hi} ပျမ်းမျှနှင့် ({base:.1f} °C)",
  "vs_full": "ကာလအပြည့် ပျမ်းမျှနှင့် ({base:.1f} °C)",
  "heatmap_title": "နှစ်အလိုက် လစဉ်ပျမ်းမျှ အပူချိန်, {name}",
  "heatmap_cbar": "လစဉ်ပျမ်းမျှ (°C)",
  "anom_heatmap_title": "{base} နှင့် လစဉ် ကွဲလွဲမှု, {name}",
  "anom_heatmap_cbar": "{base} နှင့် ကွဲလွဲမှု (°C)",
  "full_period": "ကာလအပြည့်",
  "dashboard_suptitle": "{name} အပူချိန်များ {start}-{end} (ရင်းမြစ်: Open-Meteo ပြန်လည်သုံးသပ်ချက်)",
  "page_title": "{name} အပူချိန်များ",
  "subtitle": "{start}-{end} · {days} ရက် · အပူဆုံး {wy} ({wv:.1f} °C), အအေးဆုံး {cy} ({cv:.1f} °C)",
  "card_trend": "ပူနွေးမှု လားရာ",
  "card_mean": "ပျမ်းမျှ နေ့စဉ်အပူချိန်",
  "card_warmest": "အပူဆုံးနှစ်",
  "card_coldest": "အအေးဆုံးနှစ်",
  "share": "မျှဝေရန်",
  "share_copied": "လင့်ခ် ကူးယူပြီး",
  "climate_news": "ရာသီဥတု သတင်းများ",
  "extreme_weather": "ပြင်းထန်သော ရာသီဥတု",
  "analog_line": "၂၀၅၀ တွင် {city} သည် ယနေ့ {analog} ကဲ့သို့ ခံစားရနိုင်သည်၊ ခန့်မှန်း +{d} °C ပိုပူသည်။",
  "analog_past": "၁၉၄၀ တွင် {city} သည် ယနေ့ {analog} ကဲ့သို့ ဖြစ်ခဲ့သည်၊ ခန့်မှန်း {d} °C ပိုအေးသည်။",
  "cap_yearly": "LOESS ချောမွေ့စေသူဖြင့် (အရှိန်မြင့်လာမှု ပြသည်) နှစ်စဉ်ပျမ်းမျှနှင့် ခိုင်မာသော Theil-Sen လားရာ + အရေးပါမှု",
  "cap_anomalies": "နှစ်တိုင်း ၁၉၆၁-၁၉၉၀ ပျမ်းမျှနှင့် နှိုင်းယှဉ်: အနီတံများ ပိုပူ၊ အပြာ ပိုအေး။ အပြာများသည်မှ အနီများသို့ ပြောင်းလဲခြင်းသည် ပူနွေးမှုဖြစ်သည်။",
  "cap_heatmap": "လတိုင်း၏ ပျမ်းမျှကို နှစ်တိုင်းအတွက် အရောင်ဇယားကွက်အဖြစ် (2 °C တန်းများ)။ ထိုလ ဆယ်စုနှစ်များအတွင်း ပူလာပုံ မြင်ရန် ကော်လံတစ်ခုကို အပေါ်သို့ ဖတ်ပါ။",
  "cap_anom_heatmap": "ဇယားကွက်တူ၊ သို့သော် လတိုင်းကို ၎င်း၏ ကိုယ်ပိုင် ၁၉၆၁-၁၉၉၀ ပုံမှန်နှင့် တိုင်းတာသည်၊ ထို့ကြောင့် ပြောင်းလဲမှုသာ မြင်ရသည် (အနီ ပုံမှန်ထက်ပူ၊ အပြာ အေး)၊ ရာသီစက်ဝန်း ဖယ်ရှားထားသည်။",
  "cap_threshold": "နှစ်တိုင်း 18 °C အထက် (ပူ) နှင့် 0 °C အောက် (အေးခဲ) ရက်များ။ ခိုင်မာသော လားရာနှစ်ခု ဖြတ်ကျော်ခြင်းသည် ယခု ပူသောရက်များက အေးခဲသောရက်များထက် များပြားကြောင်း ဆိုလိုသည်။",
  "hint": "ပိတ်ရန် မည်သည့်နေရာမဆို နှိပ်ပါ သို့မဟုတ် Esc နှိပ်ပါ",
  "site_title": "ကမ္ဘာ့မြို့များ၏ အပူချိန်များ",
  "intro": "၁၉၄၀ ကတည်းက ကမ္ဘာ့မြို့ကြီးများ ပူလာပုံ: ERA5 ရာသီဥတု ပြန်လည်သုံးသပ်ချက်မှ နေ့စဉ်အပူချိန် မှတ်တမ်းများ။",
  "map_heading": "ကမ္ဘာတစ်ဝှမ်း အပူချိန်များ",
  "map_sub": "မြေပုံပေါ်တွင် သို့မဟုတ် စာရင်းမှ မြို့တစ်ခု ရွေးပါ",
  "map_filter": "တိုက် သို့မဟုတ် နိုင်ငံ ပြပါ",
  "omni_ph": "မြို့၊ နိုင်ငံ၊ ဒေသ သို့မဟုတ် မည်သည့်နေရာမဆို ရှာပါ",
  "omni_cities": "မြို့များ",
  "omni_countries": "နိုင်ငံများ",
  "omni_regions": "တိုက်များ",
  "omni_places": "ကမ္ဘာတစ်ဝှမ်း နေရာများ",
  "omni_anywhere": "မည်သည့်နေရာမဆို စစ်ဆေးပါ: \"{q}\"",
  "nav_ranking": "အဆင့်သတ်မှတ်ချက်",
  "nav_dashboard": "ရာသီဥတု ဒက်ရှ်ဘုတ်",
  "regions": {
    "Europe": "ဥရောပ",
    "Asia": "အာရှ",
    "Middle East": "အရှေ့အလယ်ပိုင်း",
    "Africa": "အာဖရိက",
    "North America": "မြောက်အမေရိက",
    "South America": "တောင်အမေရိက",
    "Oceania": "သမုဒ္ဒရာဒေသ"
  },
  "choose_city": "မြို့တစ်ခု ရွေးပါ...",
  "back_to_map": "🗺 မြေပုံ",
  "range_title": "နှစ်များအတွင်း လစဉ် အပူချိန် အကွာအဝေး, {name}",
  "range_min_max": "အနိမ့်ဆုံး-အမြင့်ဆုံး {start}-{end}",
  "range_average": "ပျမ်းမျှ",
  "range_latest": "နောက်ဆုံး ({year})",
  "range_ylabel": "လစဉ်ပျမ်းမျှ အပူချိန် (°C)",
  "cap_range": "နှစ်များအတွင်း လတိုင်း၏ အနိမ့်ဆုံး-အမြင့်ဆုံး အကွာအဝေး၊ နောက်ဆုံးနှစ်နှင့်။ ၎င်းသည် ပူသောအစွန်းကို ကပ်နေသလား?",
  "record_title": "လစဉ် စံချိန် အမြင့်/အနိမ့် နေ့စဉ်အပူချိန်, {name}",
  "record_band": "စံချိန် အကွာအဝေး {start}-{end}",
  "record_latest_high": "{year} အမြင့်များ",
  "record_latest_low": "{year} အနိမ့်များ",
  "record_ylabel": "နေ့စဉ်အပူချိန် (°C)",
  "cap_records": "လတိုင်း၏ အချိန်တိုင်း စံချိန် နေ့စဉ်အမြင့်နှင့်အနိမ့်၊ နောက်ဆုံးနှစ်၏ အစွန်းများနှင့်",
  "volatility_title": "တစ်နှစ်လျှင် နေ့စဉ် အပူချိန် အတက်အကျများ, {name}",
  "volatility_jump": "နေ့စဉ် ခုန်ကူးမှု",
  "volatility_ylabel": "ခုန်ကူးမှုကြီးသော ရက်များ",
  "cap_volatility": "တစ်နှစ်လျှင် နေ့စဉ် အပူချိန် ခုန်ကူးမှုကြီးများ မည်မျှ ဖြစ်ပွားသည် (≥6 °C)၊ အပူချိန် ကွဲပြားမှု",
  "per_decade_mm": "မီလီမီတာ / ဆယ်စုနှစ်",
  "precip_title": "နှစ်စဉ် မိုးရေချိန်, {name}",
  "precip_ylabel": "မိုးရေချိန် (မီလီမီတာ / နှစ်)",
  "precip_annual": "နှစ်စဉ် စုစုပေါင်း",
  "cap_precip": "စုစုပေါင်း နှစ်စဉ် မိုးရေချိန် (မိုးရေနှင့် နှင်းရေ) လားရာနှင့်",
  "stripes_title": "ပူနွေးမှု အစင်းများ, {name}",
  "stripes_cbar": "{lo}-{hi} နှင့် ကွဲလွဲမှု (°C)",
  "cap_stripes": "အစင်းတစ်ခုစီသည် တစ်နှစ်၏ အပူချိန်: အပြာ ပိုအေး၊ အနီ ၁၉၆၁-၁၉၉၀ ပျမ်းမျှထက် ပိုပူ။ အပြာမှ အနီသို့ ရွေ့လျားခြင်းသည် ပူနွေးမှုဖြစ်ပြီး၊ အရောင်မှလွဲ၍ ဖတ်စရာ မရှိပါ။",
  "season_title": "စိုက်ပျိုးရာသီ အရှည်, {name}",
  "season_ylabel": "စိုက်ပျိုးရာသီ အရှည် (ရက်)",
  "season_annual": "ရာသီ အရှည်",
  "cap_season": "နှစ်တိုင်း အပူ စိုက်ပျိုးရာသီ၏ အရှည် (နေ့စဉ်ပျမ်းမျှ ≥ 5 °C ရှိသော ဆက်တိုက်ရက်များ): လယ်ယာစိုက်ပျိုးရေး မှီခိုသော နှင်းခဲကင်း ကာလ၊ ရာသီဥတု ပူလာသည်နှင့်အမျှ ရှည်လာသည်။",
  "dtr_title": "နေ့ခင်း အပူချိန် အကွာအဝေး (နေ့ − ည), {name}",
  "dtr_ylabel": "ပျမ်းမျှ နေ့စဉ် အမြင့် − အနိမ့် (°C)",
  "dtr_annual": "နှစ်စဉ်ပျမ်းမျှ အကွာအဝေး",
  "cap_dtr": "နေ့စဉ် အမြင့်နှင့် အနိမ့်ကြား ပျမ်းမျှ ကွာဟမှု။ ကျုံ့လာသော အကွာအဝေးသည် ဖန်လုံအိမ် လက်ဗွေ: နေ့ထက် ည ပိုမြန်စွာ ပူလာခြင်း၊ ကျယ်လာသော အကွာအဝေးသည် ခြောက်သွေ့မှုကို ညွှန်ပြနိုင်သည်။",
  "seasonshift_title": "ရာသီစက်ဝန်း ဘယ်လိုရွေ့သွားသလဲ, {name}",
  "seasonshift_ylabel": "လစဉ်ပျမ်းမျှ အပူချိန် (°C)",
  "cap_seasonshift": "မှတ်တမ်း၏ ပထမ နှင့် နောက်ဆုံး ဆယ်စုနှစ်အတွက် ပျမ်းမျှနှစ်။ လတိုင်း၌ မျဉ်းကွေးများကြား ကွာဟမှုသည် နှစ်၏ မည်သည့်အပိုင်းများ အပူဆုံး ဖြစ်ခဲ့ကြောင်း ပြသည် (မကြာခဏ နွေရာသီထက် ဆောင်းရာသီ ပို)။",
  "health_heading": "ကျန်းမာရေး-သက်ရောက်မှု ညွှန်းကိန်းများ",
  "health_sub": "အထက်ပါ ပူနွေးမှု လားရာများ အသိအမှတ်ပြု အပူ၊ အအေးနှင့် အလွန်အကျွံ-ဖြစ်ရပ် ထိတွေ့မှု တိုင်းတာချက်များအဖြစ် ဘယ်လို ပြောင်းလဲသည်။ လိုအပ်သော ဒေတာ ရရှိနိုင်သည့်နေရာတွင် ဇယားတစ်ခုစီ ပေါ်လာသည်။",
  "degreedays_title": "အပူပေးခြင်းနှင့် အအေးပေးခြင်း ဒီဂရီ-ရက်များ, {name}",
  "dd_ylabel": "တစ်နှစ်လျှင် ဒီဂရီ-ရက်များ (°C·ရက်)",
  "hdd_label": "အပူပေးခြင်း (< {t:.0f} °C)",
  "cdd_label": "အအေးပေးခြင်း (> {t:.0f} °C)",
  "per_decade_dd": "°C·ရက် / ဆယ်စုနှစ်",
  "cap_degreedays": "နှစ်စဉ် အပူ-သက်တောင့်သက်သာ ဝန်: အပူပေးရန် လိုအပ်ချက် (18 °C အောက်) လျော့ကျပြီး အအေးပေးရန် လိုအပ်ချက် (22 °C အထက်) မြင့်တက်သည်၊ အအေး ထိတွေ့မှုနှင့် လေအေးပေးစက် လိုအပ်ချက်၏ ကိုယ်စားပြုချက်။",
  "heatwave_title": "တစ်နှစ်လျှင် အပူလှိုင်း ရက်များ, {name}",
  "heatwave_ylabel": "တစ်နှစ်လျှင် အပူလှိုင်း ရက်များ",
  "heatwave_series": "အပူလှိုင်း ရက်များ",
  "cap_heatwave": "အပူလှိုင်းအတွင်း ရက်များ: နေ့စဉ်အမြင့် ဒေသ ၁၉၆၁-၁၉၉၀ ၉၀ ရာခိုင်နှုန်းအထက် ရှိသော ≥၃ ရက် ဆက်တိုက်။ ဆက်လက်ဖြစ်ပေါ်နေသော နေ့ခင်းအပူသည် အပူလှိုင်း ပိုလျှံသေဆုံးမှု၏ အဓိကအကြောင်းရင်း။",
  "tropic_title": "တစ်နှစ်လျှင် အပူပိုင်း ညများ, {name}",
  "tropic_ylabel": "တစ်နှစ်လျှင် ညများ",
  "tropic_series": "ညများ ≥ {t:.0f} °C",
  "cap_tropic": "အနိမ့် 20 °C သို့မဟုတ် အထက်တွင် ကျန်ရှိသော ညများ၊ ထို့ကြောင့် ခန္ဓာကိုယ်သည် ညအတွင်း သက်သာမှု မရရှိ၊ အပူဆိုင်ရာ သေဆုံးမှု၏ အဓိက၊ မကြာခဏ လျစ်လျူရှုခံရသော အကြောင်းရင်း။",
  "coldspell_title": "တစ်နှစ်လျှင် အအေးလှိုင်း ရက်များ, {name}",
  "coldspell_ylabel": "တစ်နှစ်လျှင် အအေးလှိုင်း ရက်များ",
  "coldspell_series": "အအေးလှိုင်း ရက်များ",
  "cap_coldspell": "အအေးလှိုင်းအတွင်း ရက်များ: နေ့စဉ်အနိမ့် ဒေသ ၁၉၆၁-၁၉၉၀ ၁၀ ရာခိုင်နှုန်းအောက် ရှိသော ≥၃ ရက် ဆက်တိုက်။ ကြာရှည်သော အအေးသည် ဆောင်းရာသီ နှလုံးနှင့် အသက်ရှူလမ်းကြောင်း ပိုလျှံသေဆုံးမှုကို ဖြစ်စေသည်။",
  "heavyrain_title": "တစ်နှစ်လျှင် မိုးသည်းထန်သောရက်များ, {name}",
  "heavyrain_ylabel": "တစ်နှစ်လျှင် ရက်များ",
  "heavyrain_series": "ရက်များ ≥ {mm:.0f} မီလီမီတာ",
  "cap_heavyrain": "အနည်းဆုံး 20 မီလီမီတာ မိုးရွာသောရက်များ (ETCCDI R20mm)၊ ရေကြီးမှုကို ဖြစ်စေသော မိုးသည်းထန်မှုများသည် ဒဏ်ရာ၊ နေရပ်စွန့်ခွာမှုနှင့် ရေမှတစ်ဆင့် ကူးစက်ရောဂါများကို ဆောင်ကြဉ်းသည်။",
  "heatindex_title": "တစ်နှစ်လျှင် အန္တရာယ်ရှိ အပူညွှန်းကိန်း ရက်များ, {name}",
  "heatindex_ylabel": "တစ်နှစ်လျှင် ရက်များ",
  "heat_strong": "≥ {t:.0f} °C (အထူးသတိထားရန်)",
  "heat_danger": "≥ {t:.0f} °C (အန္တရာယ်)",
  "cap_heatindex": "ခံစားရသော အပူချိန် (အစိုဓာတ်ပါဝင်သော အပူညွှန်းကိန်း) အပူ-ဖိစီးမှု အဆင့်များ ရောက်ရှိသောရက်များ၊ အများပြည်သူ အပူသတိပေးချက်များ အသုံးပြုသော တိုင်းတာချက်။ ခံစားရသော-အပူချိန် ဒေတာ လိုအပ်သည်။",
  "footer": "ဖန်တီးသည် {date} · ဒေတာ <a href=\"https://open-meteo.com/\">Open-Meteo</a> သမိုင်းဝင် ပြန်လည်သုံးသပ်ချက် (ERA5) မှ · <a href=\"https://github.com/YASoftwareDev/temperatury\">GitHub ရှိ ရင်းမြစ်</a>",
  "map_coverage": "ယခုအထိ မြို့ {total} ခုအနက် {done} ခုကို ခွဲခြမ်းစိတ်ဖြာပြီးပါပြီ - ကျန်များကို နေ့စဉ်ထည့်နေပါသည်။",
  "map_coverage_help": "ဒေတာစုဆောင်းရာတွင် ကူညီပါ",
  "qv_nodata": "ဤမြို့အတွက် ဒေတာမရှိသေးပါ။",
  "qv_nearest": "အနီးဆုံး ခွဲခြမ်းစိတ်ဖြာပြီးမြို့",
  "cur_so_far": "{year} ယခုအထိ ({month} {day} ရက်အထိ): ပျမ်းမျှ {v} °C၊ နှစ်၏တူညီသောရက်များအတွက် 1961-1990 ပျမ်းမျှနှင့်နှိုင်းယှဉ်လျှင် {d} °C။",
  "cmp_title": "မြို့နှစ်မြို့ နှိုင်းယှဉ်ရန်",
  "cmp_hint": "မျဉ်းကွေးတစ်ခုစီသည် ထိုမြို့၏ ကိုယ်ပိုင် 1961-1990 ပျမ်းမျှနှင့် နှိုင်းယှဉ်သော နှစ်စဉ်သွေဖည်မှုဖြစ်၍ ရာသီဥတုကွဲပြားသောနေရာများကို မျှတစွာနှိုင်းယှဉ်နိုင်သည်။",
  "cmp_city_a": "ပထမမြို့",
  "cmp_city_b": "ဒုတိယမြို့",
  "kpi_rate": "ကမ္ဘာ့ပူနွေးမှုနှုန်း",
  "kpi_since": "1940 မှစ၍ ကမ္ဘာ့ပူနွေးမှု",
  "kpi_cities": "ခွဲခြမ်းစိတ်ဖြာပြီးမြို့များ",
  "kpi_warmest": "အပူဆုံးနှစ် (ကမ္ဘာ့ပျမ်းမျှ)",
  "sum_season": "ဤနေရာတွင် အမြန်ဆုံးပူနွေးလာသောရာသီ: {season} (ဆယ်စုနှစ်လျှင် {v} °C)။",
  "sum_month": "ဤနေရာတွင် အမြန်ဆုံးပူနွေးလာသောလ: {month} (ဆယ်စုနှစ်လျှင် {v} °C)။",
  "season_winter": "ဆောင်း",
  "season_spring": "နွေဦး",
  "season_summer": "နွေ",
  "season_autumn": "ဆောင်းဦး",
  "grid_alias_note": "အပူချိန်မှတ်တမ်းကို ~11 ကီလိုမီတာ ရာသီဥတုဒေတာ ကွက်ကွက်တစ်ခုစီအလိုက် တွက်ချက်သည်။ {alias} သည် ၎င်း၏ကွက်ကို {city} နှင့် မျှဝေထားသဖြင့် နှစ်ခုစလုံး ၁၉၄၀ မှစ၍ တူညီသောမှတ်တမ်းကို ပြသသည်။",
  "qv_baseline": "1961-1990 အခြေခံစာတန်းနှင့် ဆယ်စုနှစ် ပျမ်းမျှ",
  "qv_chart_alt": "ဆယ်စုနှစ်တစ်ခုပြီးတစ်ခု ပူနွေးလာမှု၊ ဧရိယာအပြည့်ဇယား"
}
